MANIFEST.in
VERSION
setup.py
libapi.woocommerce.egg-info/PKG-INFO
libapi.woocommerce.egg-info/SOURCES.txt
libapi.woocommerce.egg-info/dependency_links.txt
libapi.woocommerce.egg-info/requires.txt
libapi.woocommerce.egg-info/top_level.txt
libapi/woocommerce/__init__.py
libapi/woocommerce/package.json
libapi/woocommerce/schema/__init__.py
libapi/woocommerce/schema/v3/__init__.py
libapi/woocommerce/schema/v3/product.py
libapi/woocommerce/schema/v3/productattributeref.py
libapi/woocommerce/schema/v3/productcatalogvisibility.py
libapi/woocommerce/schema/v3/productcategoryref.py
libapi/woocommerce/schema/v3/productdefaultattribute.py
libapi/woocommerce/schema/v3/productdimensions.py
libapi/woocommerce/schema/v3/productdownload.py
libapi/woocommerce/schema/v3/productimage.py
libapi/woocommerce/schema/v3/productmetadataproperty.py
libapi/woocommerce/schema/v3/productstatus.py
libapi/woocommerce/schema/v3/producttagref.py
libapi/woocommerce/schema/v3/producttype.py
libapi/woocommerce/schema/v3/productvariation.py
libapi/woocommerce/schema/v3/resourcelink.py
libapi/woocommerce/schema/v3/woocommercemodel.py
libapi/woocommerce/types/__init__.py
libapi/woocommerce/types/iwoocommerceclient.py